mouse_keyboard_tracker/__init__.py
mouse_keyboard_tracker/cli.py
mouse_keyboard_tracker/config.py
mouse_keyboard_tracker/eventos.py
mouse_keyboard_tracker/log_manager.py
mouse_keyboard_tracker/logger.py
mouse_keyboard_tracker/ociosidade.py
mouse_keyboard_tracker-0.1.3.dist-info/METADATA
mouse_keyboard_tracker-0.1.3.dist-info/WHEEL
mouse_keyboard_tracker-0.1.3.dist-info/entry_points.txt
mouse_keyboard_tracker-0.1.3.dist-info/top_level.txt
mouse_keyboard_tracker-0.1.3.dist-info/RECORD
