Metadata-Version: 2.1
Name: mouse_keyboard_tracker
Version: 0.1.3
Summary: Uma biblioteca para monitorar atividades de teclado e mouse.
Home-page: https://github.com/victorlcastro-dsa/mouse-keyboard-tracker
Author: Victor L. Castro
Author-email: victorlcastro.dsa@gmail.com
Classifier: Programming Language :: Python :: 3
Classifier: Operating System :: OS Independent
Requires-Python: >=3.6
Requires-Dist: pynput
